sdmc_adhoc_processing/__init__.py
sdmc_adhoc_processing/constants.py
sdmc_adhoc_processing/data_dictionary_TEMPLATE.xlsx
sdmc_adhoc_processing/data_dictionary_nonstandard_vars.xlsx
sdmc_adhoc_processing/generate_README.py
sdmc_adhoc_processing/generate_dict.py
sdmc_adhoc_processing/process.py
sdmc_adhoc_processing/readme_template.md
sdmc_adhoc_processing/regenerate_README.py
sdmc_adhoc_processing/utilities.py
sdmc_adhoc_processing-0.1.47.dist-info/LICENSE
sdmc_adhoc_processing-0.1.47.dist-info/METADATA
sdmc_adhoc_processing-0.1.47.dist-info/WHEEL
sdmc_adhoc_processing-0.1.47.dist-info/entry_points.txt
sdmc_adhoc_processing-0.1.47.dist-info/top_level.txt
sdmc_adhoc_processing-0.1.47.dist-info/RECORD
